{
  "utilScanGlasPlain" : "Scan Glas",
  "procurementWindowPageChooseWindowTypeText" : "Vælg solafskærmende eller energirude",
  "settingsDropdownChangeDesignText" : "Skift dit design",
  "insertMeasurementPageHeightText" : "Højde",
  "utilGallery" : "Galleri",
  "loginPageForgotPassword" : "Glemt adgangskode",
  "procurementPricePageChangeAddonsText" : "Redigere i tilvalg",
  "measureToolPageRequisitionNo" : "Rekv. Nr.",
  "utilPrice" : "Pris",
  "chooseFigurePageGlassDimensionsText" : "Glasmål",
  "insertMeasurementPageDepthText" : "Dybde",
  "utilNext" : "Næste",
  "chooseFigurePageShapeText" : "Facon",
  "insertMeasurementPageMMText" : "mm",
  "menuPageMessages" : "Beskeder fra Scan Glas",
  "utilDate" : "Dato",
  "procurementWindowPageOrnamentText" : "Ornament",
  "procurementWindowPageManuelText" : "Manuel",
  "utilChooseFigure" : "Valg af figur",
  "utilCustomerNo" : "Kunde Nr.",
  "utilName" : "Navn",
  "utilBack" : "Tilbage",
  "notesPagePlacementText" : "Placering",
  "utilProcurement" : "Tilbudsgivning",
  "galleryPageChooseGalleryText" : "Vælg galleri",
  "insertMeasurementPageFrontText" : "Front",
  "utilPlaceholderWriteText" : "Skriv tekst",
  "insertMeasurementProfileText" : "Profil",
  "utilOrderNo" : "Ordre Nr.",
  "measureToolPageFullName" : "Fulde navn",
  "utilGlazer" : "Glarmester",
  "sideMenuViewTotalPriceText" : "Samlet pris inkl. moms",
  "measureToolPageFindExistingCustomer" : "Find eksisterende kunde",
  "loginPageHeader" : "Log ind",
  "procurementPricePageCloseAddonsInfoText" : "Luk tilvalgsinfo",
  "sideMenuViewSendToArchiveButtonText" : "Send til arkiv",
  "chooseFigurePageMeasureInsideOutsideText" : "Opmåling indefra eller udefra",
  "utilDone" : "Færdig",
  "notesPageDirectionText" : "Retning",
  "loginPageRememberPassword" : "Husk adgangskode",
  "utilAddress" : "Adresse",
  "notesPageTakeNotesText" : "Tag noter",
  "measureToolPagePoliceNo" : "Police Nr.",
  "procurementWindowPageChooseWindowFunctionText" : "Vælg rudens funktion",
  "chooseFigurePageOutsideText" : "Udefra",
  "galleryPageInsertNameText" : "Tilføj navn",
  "utilAboutGlass" : "Viden om glas",
  "chooseFigurePageFoldDimensionsText" : "Falsmål",
  "utilOk" : "OK",
  "utilPhoneShort" : "Tlf. Nr.",
  "measureToolPageEANNo" : "EAN Nr.",
  "menuPageEnergyCalc" : "Energi beregner",
  "insertMeasurementPageSurfaceText" : "Fladen",
  "utilLogin" : "Login",
  "insertMeasurementTotalDepthText" : "Total dybde",
  "notesPageHeaderText" : "Noter",
  "utilEmail" : "E-mail",
  "procurementWindowPageEnergyWindowText" : "Energirude",
  "procurementWindowPageSmallCleaningText" : "Let rens",
  "notesPageUploadNewPictureButtonText" : "Upload nyt billede",
  "settingsDropdownYourNumbersText" : "Dine beløb",
  "chooseFigurePageInsideText" : "Indefra",
  "insertMeasurementPageSectionText" : "Tværsnit",
  "chooseShapePageChooseShapeText" : "Vælg facon",
  "measureToolPageDamageNo" : "Skade Nr.",
  "sideMenuViewSendToCustomerButtonText" : "Send til kunde",
  "settingsDropdownYourInformationText" : "Dine oplysninger",
  "utilCity" : "By",
  "sideMenuViewCurrencyText" : "DKK",
  "sideMenuViewMenuText" : "Menu",
  "measureToolPageCustomerSameAsPayer" : "Kunde er samme som fakturamodtager",
  "redHeaderBannerLeftText" : "Glarmester [glazerName]",
  "utilCreate" : "Opret",
  "procuremntWindowPageSunBlockText" : "Solafskærmende",
  "utilZip" : "Post Nr.",
  "utilScanGlas" : "I samarbejde med Scan Glas",
  "insertMeasurementPageRadiusText" : "Radius",
  "utilPlaceholderSearchForOfferText" : "Søg efter tilbud",
  "infoAboutGlassPageProductCatalog" : "Produktkatalog",
  "procurementWindowPageSoundText" : "Lyd",
  "chooseFigurePageLightDimensionsText" : "Lysmål",
  "sideMenuViewPicturesAndNotesButtonText" : "Billeder & noter",
  "galleryPageAddOfferText" : "Tilføj tilbud",
  "procurementPricePageUVFilterText" : "UV Filter",
  "sideMenuViewAddNewWindowButtonText" : "Tilføj ny rude",
  "notesPagePicturesOfMeasurementText" : "Billeder af opmåling",
  "infoAboutGlassPageGuides" : "Vejledninger",
  "utilProjectFolder" : "Projekt mappe",
  "sideMenuViewMeasurementText" : "Opmålinger",
  "chooseFigurePageChooseMeasureGripText" : "Vælg målgreb",
  "procurementPricePageDeleteOfferText" : "Slet tilbud",
  "galleryPagePlaceholderInsertName" : "Insæt navn",
  "galleryPageBottomMenuText" : "Swipe til venstre, for at se tidligere albums",
  "infoAboutGlassPageVocabulary" : "Glas ordbog",
  "menuPageMeasureTool" : "Opmålingsværktøj",
  "procurementPricePageAddonsText" : "Tilvalg",
  "procurementPricePageExtraFieldButtonText" : "Ekstra felt",
  "insertMeasurementPageWidthText" : "Bredde",
  "insertMeasurementGlassText" : "Glas",
  "chooseFigurePageSquareText" : "Firkant",
  "settingsDropdownLogoutText" : "Log ud",
  "procurementPricePageAddToOrderText" : "Tilføj til bestilling",
  "galleryPageUploadNewGalleryButtonText" : "Upload nyt galleri",
  "sideMenuViewContactInfoText" : "Stamdata",
  "utilContactPerson" : "Kontaktperson",
  "procurementPricePageSoundProofText" : "Lydisolering",
  "procurementWindowPageSafetyText" : "Sikkerhed",
  "frontPageFindGlazer" : "Find glarmester",
  "chooseFigurePageChooseGeometriText" : "Vælg geometri",
  "galleryPageCreateGalleryText" : "Opret galleri",
  "loginPageUsernameText" : "Brugernavn",
  "loginPagePasswordText" : "Adgangskode"
}
